[
  {
    "id": "emergency-safety",
    "name": "독거노인·장애인 응급안전안심서비스",
    "aliases": ["응급안전안심", "응급안전알림서비스", "독거노인 응급안전", "ICT 응급안전"],
    "situations": ["가족환경", "권리안전"],
    "attributeTags": [],
    "target": "parent",
    "agency": "보건복지부",
    "track": "서비스",
    "phone": "129",
    "eligibility": {
      "summary": "혼자 사는 만 65세 이상 노인 누구나(2026년 소득기준 폐지). 노인 2인 가구·조손가구, 활동지원 수급 취약 장애인 등 포함",
      "slots": { "age": ">=65", "household": "독거 또는 노인2인·조손", "income": "기준 없음(2026 폐지)" },
      "incomeRule": "2026년 독거노인 소득기준 폐지 — 혼자 사는 만65세↑ 누구나",
      "confidence": "확인"
    },
    "deadline": { "type": "상시", "note": "신청 후 댁내 ICT 감지기 설치까지 대기 가능" },
    "howToApply": { "online": null, "offline": "읍면동 행정복지센터·노인복지관 방문 또는 전화 신청" },
    "applyUrl": "https://www.gov.kr/portal/service/serviceInfo/WII000000320",
    "wlfareInfoId": null,
    "documents": ["응급안전안심서비스 신청서", "신분증"],
    "procedure": ["읍면동 행정복지센터·노인복지관에 방문 또는 전화 신청", "대상 선정", "댁내 ICT 감지기(화재·활동·응급호출 등) 무료 설치", "지역센터·소방서 연계 24시간 모니터링"],
    "sequence": { "order": 1, "prerequisiteOf": [], "exclusiveWith": [] },
    "exclusiveWith": [],
    "timeline": "지금",
    "amount": "감지기 무료 설치(본인부담 없음)",
    "regionVaries": false,
    "source": { "url": "https://www.gov.kr/portal/service/serviceInfo/WII000000320", "verifiedAt": "2026-06-23" },
    "notes": "2026년 지침 개정으로 독거노인 소득기준 폐지(혼자 사는 만65세↑ 누구나). 화재·응급호출·장시간 쓰러짐 감지 등 ICT 기기 무료 설치. 24시간 정부지원 활동지원 수급자는 제외. 권리안전 분류와 공유(주인=가족환경). 문의 보건복지상담센터 129. 출처: 보건복지부 보도자료(혼자 사시는 노인 누구나 신청 가능)."
  },
  {
    "id": "solo-elder-checkin",
    "name": "독거노인 돌봄기본서비스(안부확인·안전확인)",
    "aliases": ["독거노인 안부확인", "안전확인서비스", "생활관리사 방문", "안부전화"],
    "situations": ["가족환경", "권리안전"],
    "attributeTags": [],
    "target": "parent",
    "agency": "보건복지부(독거노인종합지원센터)",
    "track": "서비스",
    "phone": "1661-2129",
    "eligibility": {
      "summary": "만 65세 이상 독거노인 중 보호 필요(사회활동·접촉·식사·건강 등 평가). 대부분 노인맞춤돌봄서비스로 통합 제공",
      "slots": { "age": ">=65", "household": "독거", "need": "안전·정서 돌봄 필요" },
      "incomeRule": null,
      "confidence": "잠재후보"
    },
    "deadline": { "type": "상시", "note": "선정조사 후 수행기관 매칭" },
    "howToApply": { "online": "복지로(노인맞춤돌봄 신청)", "offline": "읍면동 행정복지센터 방문" },
    "applyUrl": "https://www.bokjiro.go.kr/ssis-tbu/twataa/wlfareInfo/moveTWAT52011M.do?wlfareInfoId=WLF00003191",
    "wlfareInfoId": "WLF00003191",
    "documents": ["신분증", "주민등록등본"],
    "procedure": ["읍면동 또는 복지로 신청", "대상자 선정조사(욕구·상태)", "수행기관 매칭", "생활관리사 주 1회 방문·주 2~3회 전화로 안전·안부 확인, 말벗·정서지원"],
    "sequence": { "order": 1, "prerequisiteOf": [], "exclusiveWith": ["elderly-customized-care"] },
    "exclusiveWith": ["elderly-customized-care"],
    "timeline": "지금",
    "amount": "무료",
    "regionVaries": false,
    "source": { "url": "https://www.1661-2129.or.kr/sub02/sub020103.do", "verifiedAt": "2026-06-23" },
    "notes": "현재 독거노인 돌봄기본서비스는 노인맞춤돌봄서비스(elderly-customized-care, 주인=노쇠치매)로 통합 운영되므로 사실상 동일 트랙 — 중복 신청 불가, 노인맞춤돌봄 항목과 조정 필요. 안부확인(방문 주1회↑·전화 주2회↑), 말벗·정서지지 포함. 독거노인종합지원센터 1661-2129."
  },
  {
    "id": "household-change-recheck",
    "name": "가구원 변경 시 복지급여 재점검",
    "aliases": ["가구원 변경 복지 재점검", "사별 후 복지 재신청", "세대분리 복지 재산정"],
    "situations": ["가족환경", "경제주거"],
    "attributeTags": [],
    "target": "parent",
    "agency": "읍면동 행정복지센터",
    "track": "행정절차",
    "phone": "129",
    "eligibility": {
      "summary": "배우자 사망·자녀 분가 등 가구원 변동이 생긴 노인 가구. 소득인정액·가구원 수 재산정으로 기초연금·기초생활·각종 감면 자격 변동 가능",
      "slots": { "event": "가구원 변경(사별·분가 등)", "household": "재산정 대상" },
      "incomeRule": null,
      "confidence": "잠재후보"
    },
    "deadline": { "type": "사건상대기한", "note": "가구원 변동(사망신고·전입신고) 후 신속히 복지급여 변경 신청 권장" },
    "howToApply": { "online": "복지로", "offline": "읍면동 행정복지센터 방문" },
    "applyUrl": "https://www.bokjiro.go.kr",
    "wlfareInfoId": null,
    "documents": ["신분증", "주민등록등본", "가족관계증명서", "(해당 시)사망진단서·사망신고 확인"],
    "procedure": ["가구원 변동 발생(배우자 사망·자녀 분가 등)", "주민등록 변경(사망신고·세대분리)", "읍면동에 복지급여 변경·재산정 신청", "소득인정액·가구특성 재조사", "기초연금·기초생활·요금감면 등 자격 재결정"],
    "sequence": { "order": 1, "prerequisiteOf": [], "exclusiveWith": [] },
    "exclusiveWith": [],
    "timeline": "지금",
    "amount": "지역마다 다름 → 링크 확인",
    "regionVaries": true,
    "source": { "url": "https://www.bokjiro.go.kr", "verifiedAt": "2026-06-23" },
    "notes": "단일 명명 제도가 아니라 '사건(가구원 변동) → 기존 복지급여 재산정' 안내용 행정절차 항목. 1인 가구화 시 기초연금 선정기준액·기초생활 기준중위소득 비율이 단독가구 기준으로 바뀌어 신규 자격이 생길 수 있음. 사별 시 survivor-pension(유족연금, 주인=말기임종)도 함께 점등 — 여기서는 정의하지 않고 안내만."
  },
  {
    "id": "iot-loneliness-monitoring",
    "name": "스마트(IoT·AI) 안부확인 서비스",
    "aliases": ["스마트플러그 안부확인", "AI 안부전화", "IoT 고독사 예방", "1인가구 안부살핌"],
    "situations": ["가족환경", "권리안전"],
    "attributeTags": [],
    "target": "parent",
    "agency": "지방자치단체(시·도)",
    "track": "서비스",
    "phone": "129",
    "eligibility": {
      "summary": "독거노인 등 사회적 고립·고독사 위험 가구. 대상·요건은 지자체별 상이",
      "slots": { "household": "독거·고립위험", "region": "지자체별 운영" },
      "incomeRule": null,
      "confidence": "미확인"
    },
    "deadline": { "type": "상시", "note": "지자체 모집·예산에 따라 상이" },
    "howToApply": { "online": null, "offline": "관할 읍면동 행정복지센터·시군구 복지부서 문의" },
    "applyUrl": "https://www.bokjiro.go.kr",
    "wlfareInfoId": null,
    "documents": ["신분증"],
    "procedure": ["관할 지자체·읍면동에 신청·문의", "대상 선정", "스마트플러그·IoT 감지기·AI 안부전화 등 설치·연계", "전력·활동 패턴 이상 감지 시 관제센터·담당자 대응"],
    "sequence": { "order": 1, "prerequisiteOf": [], "exclusiveWith": [] },
    "exclusiveWith": [],
    "timeline": "지금",
    "amount": "지역마다 다름 → 링크 확인",
    "regionVaries": true,
    "source": { "url": "https://news.seoul.go.kr/welfare/archives/567469", "verifiedAt": "2026-06-23" },
    "notes": "서울시 등 다수 지자체가 스마트플러그·AI안부전화·1인가구 안부살핌 등 다양한 유형으로 운영(서울시 기준 5종). 전국 단일 제도가 아니라 지자체 사업이므로 대상·명칭·연락처 상이 → 미확인, 관할 지자체 재확인 필요. 응급안전안심서비스(emergency-safety)와 기능 일부 중복."
  },
  {
    "id": "solo-elder-friend-making",
    "name": "독거노인 친구만들기 사업(정서지원)",
    "aliases": ["독거노인 친구만들기", "노인 정서지원", "말벗상담", "사랑잇는전화"],
    "situations": ["가족환경", "권리안전"],
    "attributeTags": [],
    "target": "parent",
    "agency": "보건복지부(독거노인종합지원센터)",
    "track": "서비스",
    "phone": "1661-2129",
    "eligibility": {
      "summary": "가족·이웃과 관계가 단절되고 우울·고립 위험이 있는 독거노인. 운영기관별 대상 선정",
      "slots": { "household": "독거", "need": "정서·관계 지원, 우울·고립 위험" },
      "incomeRule": null,
      "confidence": "잠재후보"
    },
    "deadline": { "type": "정기모집", "note": "수행기관(지역사회보장협의체·복지관)별 모집 시기 상이" },
    "howToApply": { "online": null, "offline": "관할 노인복지관·지역 수행기관·읍면동 문의" },
    "applyUrl": "https://www.1661-2129.or.kr/sub02/sub020301.do",
    "wlfareInfoId": null,
    "documents": ["신분증"],
    "procedure": ["관할 수행기관(복지관·지사협 등) 또는 독거노인종합지원센터 문의", "대상 선정", "집단·개별 정서지원 프로그램, 말벗상담, 자조모임 등 참여", "사회적 관계망 형성으로 우울·고독사 예방"],
    "sequence": { "order": 1, "prerequisiteOf": [], "exclusiveWith": [] },
    "exclusiveWith": [],
    "timeline": "지금",
    "amount": "무료",
    "regionVaries": true,
    "source": { "url": "https://www.1661-2129.or.kr/sub02/sub020301.do", "verifiedAt": "2026-06-23" },
    "notes": "독거노인종합지원센터의 정서지원·고독사 예방 사업(친구만들기, 말벗상담, 사랑잇는전화 등). 수행기관·지역별 운영이라 대상·모집 상이 → regionVaries. 사별·우울 동반 시 가족환경 분류 정서 트랙으로 점등. 우울 심화 시 정신건강복지센터 연계 별도."
  },
  {
    "id": "postal-safety-check",
    "name": "안부살핌 우편서비스(집배원 안부확인)",
    "aliases": ["우체국 안부살핌", "집배원 안부확인", "안부살핌 우편"],
    "situations": ["가족환경", "권리안전"],
    "attributeTags": [],
    "target": "parent",
    "agency": "행정안전부·우정사업본부(우체국공익재단)·지자체",
    "track": "서비스",
    "phone": "129",
    "eligibility": {
      "summary": "독거노인 등 고독사·고립 위험 가구. 선정 지자체 한정 운영, 대상 지자체별 상이",
      "slots": { "household": "독거·고립위험", "region": "선정 지자체 한정" },
      "incomeRule": null,
      "confidence": "미확인"
    },
    "deadline": { "type": "정기모집", "note": "행안부 공모 선정 지자체에서만 운영" },
    "howToApply": { "online": null, "offline": "관할 시군구·읍면동 복지부서 문의" },
    "applyUrl": "https://www.bokjiro.go.kr",
    "wlfareInfoId": null,
    "documents": ["신분증"],
    "procedure": ["선정 지자체 거주 여부 확인", "관할 읍면동·시군구 문의·신청", "집배원이 1~4주 단위 방문해 물품 전달·안부 확인·건강/주거 점검", "파악된 위기정보를 지자체로 전달·연계"],
    "sequence": { "order": 1, "prerequisiteOf": [], "exclusiveWith": [] },
    "exclusiveWith": [],
    "timeline": "지금",
    "amount": "지역마다 다름 → 링크 확인",
    "regionVaries": true,
    "source": { "url": "https://www.incheonnews.com/news/articleView.html?idxno=435350", "verifiedAt": "2026-06-23" },
    "notes": "행정안전부 '안부살핌 우편서비스' 공모로 선정된 지자체에서만 운영(예: 인천시). 집배원이 정기 방문해 안부 확인. 전국 보편 제도 아님 → 미확인, 관할 지자체 운영 여부 재확인 필요. 1차 공식 URL 미확보(언론 보도 기반)."
  }
]
